test_app/migrations/0001_initial.py
test_app/migrations/__init__.py
vinta_django_waffle-0.15.1.dist-info/METADATA
vinta_django_waffle-0.15.1.dist-info/RECORD
vinta_django_waffle-0.15.1.dist-info/WHEEL
vinta_django_waffle-0.15.1.dist-info/top_level.txt
waffle/__init__.py
waffle/admin.py
waffle/callables.py
waffle/decorators.py
waffle/defaults.py
waffle/helpers.py
waffle/jinja.py
waffle/managers.py
waffle/middleware.py
waffle/mixins.py
waffle/models.py
waffle/testutils.py
waffle/urls.py
waffle/utils.py
waffle/views.py
waffle/locale/en_US/LC_MESSAGES/django.mo
waffle/locale/ru/LC_MESSAGES/django.mo
waffle/management/__init__.py
waffle/management/commands/__init__.py
waffle/management/commands/waffle_delete.py
waffle/management/commands/waffle_flag.py
waffle/management/commands/waffle_sample.py
waffle/management/commands/waffle_switch.py
waffle/migrations/0001_initial.py
waffle/migrations/0002_auto_20161201_0958.py
waffle/migrations/0003_update_strings_for_i18n.py
waffle/migrations/__init__.py
waffle/templates/waffle/waffle.js
waffle/templatetags/__init__.py
waffle/templatetags/waffle_tags.py
waffle/tests/__init__.py
waffle/tests/base.py
waffle/tests/test_decorators.py
waffle/tests/test_helpers.py
waffle/tests/test_management.py
waffle/tests/test_middleware.py
waffle/tests/test_mixins.py
waffle/tests/test_models.py
waffle/tests/test_templates.py
waffle/tests/test_testutils.py
waffle/tests/test_utils.py
waffle/tests/test_views.py
waffle/tests/test_waffle.py
